<?xml version="1.0" encoding="utf-8"?>
<LinearLayout xmlns:android="http://schemas.android.com/apk/res/android"
    xmlns:app="http://schemas.android.com/apk/res-auto"
    xmlns:tools="http://schemas.android.com/tools"
    android:layout_width="match_parent"
    android:layout_height="match_parent"
    tools:context=".Register"
    android:background="#f5f5f5"
    android:paddingTop="100dp">


    <TableLayout
        android:layout_width="wrap_content"
        android:layout_height="wrap_content">

        <TableRow
            android:layout_width="match_parent"
            android:layout_height="match_parent" />

        <TableRow
            android:layout_width="match_parent"
            android:layout_height="match_parent"
            android:layout_span="3"
            android:paddingTop="10dp">

            <EditText
                android:id="@+id/etlname"
                android:layout_width="355dp"
                android:layout_height="wrap_content"
                android:ems="10"
                android:hint="نام "
                android:inputType="textPersonName" />
        </TableRow>

        <TableRow
            android:layout_width="match_parent"
            android:layout_height="match_parent"
            android:paddingTop="10dp">

            <EditText
                android:id="@+id/etfamily"
                android:layout_width="wrap_content"
                android:layout_height="wrap_content"
                android:ems="10"
                android:hint="نام خانوادگی "
                android:inputType="textPersonName" />
        </TableRow>

        <TableRow
            android:layout_width="match_parent"
            android:layout_height="match_parent"
            android:paddingTop="10dp">

            <EditText
                android:id="@+id/etnumber"
                android:layout_width="wrap_content"
                android:layout_height="wrap_content"
                android:ems="10"
                android:hint="شماره دانشجویی "
                android:inputType="number" />
        </TableRow>

        <TableRow
            android:layout_width="match_parent"
            android:layout_height="match_parent"
            android:paddingTop="10dp">

            <Button
                android:id="@+id/button"
                android:layout_width="wrap_content"
                android:layout_height="wrap_content"
                android:background="#25aea7"
                android:onClick="saveInfo"
                android:text="ذخیره"
                android:textColor="#ffffff" />

        </TableRow>

        <TableRow
            android:layout_width="match_parent"
            android:layout_height="match_parent"
            android:paddingTop="10dp">

            <Button
                android:id="@+id/btnview"
                android:layout_width="wrap_content"
                android:layout_height="wrap_content"
                android:background="#25aea7"
                android:onClick="reportclick"
                android:text="گزارش"
                android:textColor="#ffffff"
                />

        </TableRow>

        <TableRow
            android:layout_width="match_parent"
            android:layout_height="match_parent">

            <TextView
                android:id="@+id/view1"
                android:layout_width="wrap_content"
                android:layout_height="wrap_content"
                android:text=""
                android:textSize="25dp" />
        </TableRow>

        <TableRow
            android:layout_width="match_parent"
            android:layout_height="match_parent">

            <TextView
                android:id="@+id/view2"
                android:layout_width="wrap_content"
                android:layout_height="wrap_content"
                android:text="" />
        </TableRow>
    </TableLayout>

    <ListView
        android:id="@+id/listview1"
        android:layout_width="match_parent"
        android:layout_height="match_parent" />


</LinearLayout>